jamofetch/__init__.py
jamofetch/jamofetch.py
jamofetch-3.7.6.dist-info/METADATA
jamofetch-3.7.6.dist-info/WHEEL
jamofetch-3.7.6.dist-info/entry_points.txt
jamofetch-3.7.6.dist-info/RECORD
