Metadata-Version: 2.1
Name: jamofetch
Version: 3.7.6
Summary: A thin wrapper to retrieve sequence from JAMO at NERSC and on Dori.
License: None
Author: Duncan Scott
Requires-Python: >=3.8
Classifier: License :: Other/Proprietary License
Classifier: Programming Language :: Python :: 3
Classifier: Programming Language :: Python :: 3.8
Classifier: Programming Language :: Python :: 3.9
Classifier: Programming Language :: Python :: 3.10
Classifier: Programming Language :: Python :: 3.11
